{
  "id": "13249",
  "title": "Perencanaan keuangan keluarga Bapak Agus pada Tabungan Bank Central Asia, Deposito Mandiri, reksadana schroder dana likuid, first state indoequity sectorial fund, bahana dana infrastruktur,",
  "abstract": "Pada perencanaan keuangan Bapak Agus dapat dilihat bahwa asset lancar dan disposable income yang dimiliki oleh Bapak Agus tergolong cukup untuk memenuhi tujuan investasi, namun belum dilakukannya perencanaan atau pengalokasian terhadap dana yang dimiliki untuk mencapai tujuan keuangan. Perencanaan ini bertujuan membantu klien, dalam mencapai tujuan keuangan mereka. Di mana pada perencanaan keuangan Bapak Agus, melakukan reinvestasi ulang pada aset. Di mana jumlah aset dan disposable income menjadi sumber utama untuk membiayai tujuan investasi untuk mencapai tujuan. Dengan menggunakan produk investasi yang mampu memberikan hasil yang lebih tinggi yang disesuaikan dengan jangka waktu kebutuhan dalam pencapaian tujuan.",
  "creators": "VELY OCTINI",
  "contributors": "Dewi Astuti (Advisor and Examination Committee); Pwee Leng (Advisor 2)",
  "publisher": "Universitas Kristen Petra",
  "language": "Indonesian",
  "theme": "Digital Theses",
  "category": "Undergraduate Thesis",
  "sub_category": "Skripsi/Undergraduate Thesis",
  "source": "Skripsi No. 37020052/MAN/2009; Vely Octini (31405060)",
  "subjects": "CORPORATIONS FINANCE; FINANCIAL STATEMENTS"
}