{
  "id": "13769",
  "title": "Dampak go public ditinjau dari analisa rasio pada industri perhotelan di PT BES",
  "abstract": "",
  "creators": "HERMIN SINTA DEWI",
  "contributors": "Drs. Sugiono Sugiharto, M.M., Ph.D. (Advisor 1); Hartono Subagio (Examination Committee 1)",
  "publisher": "Universitas Kristen Petra",
  "language": "Indonesian",
  "theme": "Digital Theses",
  "category": "Undergraduate Thesis",
  "sub_category": "Skripsi/Undergraduate Thesis",
  "source": "Skripsi No. 886/EM/1997; Hermin Sinta Dewi (31493193)",
  "subjects": "FINANCIAL STATEMENTS; GOING PUBLIC (SECURITIES)"
}