{
  "id": "14011",
  "title": "Perancangan novel grafis \" For Coffee Addict \" untuk menyuguhkan pengetahuan sejarah kopi dan resep-resep olahan kopi bagi para pecinta kopi",
  "abstract": "Tujuan perancangan novel grafis ini adalah untuk mengkomunikasikan sejarah kopi beserta resep-resep olahan kopi dalam sebuah novel grafis yang menarik dan unik bagi para pecinta kopi. Diharapkan, novel grafis yang berjudul \" For Coffee Addict \"ini sesuai judulnya, dapat menjadi suatu novel grafis yang mendapat tempat di hati para pecinta kopi dan menjadi bacaan sesuai di saat bersantai sembari meneguk nikmatnya secangkir kopi. Novel grafis ini pun dapat menghidupkan kembali novel grafis Indonesia yang lesu akhir - akhir ini. Dengan adanya novel grafis ini yang dibuat dengan eksplorasi bentuk panelling dan layout yang eksperimental dapat menjadi minyak yang membakar kreativitas para ilustator kita agar berani keluar dari ` kotak ?.",
  "creators": "DIRA GANA MAHATA",
  "contributors": "YEKTI HERLINA (Advisor 1); Alvin Raditya Sutopo (Advisor 2); Listia (Examination Committee 1)",
  "publisher": "Universitas Kristen Petra",
  "language": "Indonesian",
  "theme": "Digital Theses",
  "category": "Undergraduate Thesis",
  "sub_category": "Komik/Ilustrasi/Cergam",
  "source": "Komik dan Ilustrasi No. 00021412/DKV/2009; Dira Gana Mahata ( 42405080 )",
  "subjects": "VISUAL COMMUNICATION; BOOK COVERS; BOOK DESIGN; COMMERCIAL ART; POSTERS; GRAPHIC ARTS"
}