{
  "id": "18927",
  "title": "Hotel bintang lima di Surabaya",
  "abstract": "Laporan Perencanaan ini disusun dalam rangka memenuhi Tugas Akhir mata kuliah Merancang AR 500 periode XXVII tahun ajaran 1992 - 1993 pada jurusan Arsitektur Fakultas Teknik Universitas Kristen Petra yang berjudul: HOTEL BINTANG LIMA DI SURABAYA Dalam laporan ini diuraikan tentang hal-hal yang berkaitan dengan perencanaan sebuah hotel antara lain, latar belakang, pengertian, tujuan dan batasan proyek. Dijelaskan juga tentang aktivitas dan kebutuhan fasilitas hotel, studi ruangnya dan juga analisa tapak yang ada. Terakhir disusunlah sutu konsep perancangan yang meliputi konsep ruang dalam, konsep ruang luar dan bentuk masa yang menjadi dasar dari gambar-gambar yang akan didesain.",
  "creators": "FELICIA KURNIADJAJA",
  "contributors": "SINGGIH SUGIANTO (Advisor 2); Ir. Bisatya Widadya Maer, M.T. (Advisor and Examination Committee)",
  "publisher": "Universitas Kristen Petra",
  "language": "Indonesian",
  "theme": "Digital Theses",
  "category": "Undergraduate Thesis",
  "sub_category": "Laporan Perancangan Arsitektur",
  "source": "Laporan Perancangan Arsitektur No. Felicia Kurniadjaja (22488035)",
  "subjects": "HOTELS, TAVERNS, ETC."
}