{
  "id": "20619",
  "title": "Perencanaan pesawat mixer pengaduk bahan baku cat kapasitas 3500 kg",
  "abstract": "",
  "creators": "R. TJAHJO WIBOWO",
  "contributors": "J. LUBI (Advisor and Examination Committee)",
  "publisher": "Universitas Kristen Petra",
  "language": "Indonesian",
  "theme": "Digital Theses",
  "category": "Undergraduate Thesis",
  "sub_category": "Skripsi/Undergraduate Thesis",
  "source": "Skripsi No. 91.54.063; R. Tjahjo Wibowo (14582081)",
  "subjects": "PAINT MIXING"
}