{
  "id": "29739",
  "title": "Faktor-faktor yang memperngaruhi audit report lag di Bursa Efek Indonesia",
  "abstract": "Penelitian ini dilakukan untuk mengetahui apakah faktor-faktor profitabilitas opini audit, jenis industry, ukuran perusahaan, dan reputasi Kantor Akuntan Publik (KAP) mempengaruhi audit report lag di perusahaan-perusahaan yang terdaftar di Bursa Efek Indonesia, khususnya di tahun 2009-2011. Metode sampling yang digunakan adalah purposive sampling dengan jumlah total perusahaan sampel sebanyak 600 perusahaan. Data yang digunakan dalam penelitian ini merupakan laporan keuangan yang berasal dari www.idx.com. Pengolahan data dilakukan dengan cara melakukan uji asumsi klasik dan normalitas terlebih dahulu kemudian dilanjutkan dengan uji hipotesis. Software yang digunakan dalam mengolah data adalah SPSS versi 20. Hasil penelitian menunjukkan bahwa variabel independen dapat menjelaskan variabel dependennya sebesar 2,6%; 97,4% lainnya dijelaskan oleh faktor-faktor lain. Secara parsial, jenis industry mempengaruhi audit report lag. Sedangkan opini audit, profitabilitas, ukuran perusahaan dan reputasi KAP tidak berpengaruh terhadap audit report lag.",
  "creators": "IVENA TIONO",
  "contributors": "Dr. Yulius Jogi Christiawan, S.E., M.Si., Ak. (Advisor 1); Juniarti (Examination Committee 1)",
  "publisher": "Universitas Kristen Petra",
  "language": "Indonesian",
  "theme": "Digital Theses",
  "category": "Undergraduate Thesis",
  "sub_category": "Skripsi/Undergraduate Thesis",
  "source": "Skripsi No. 32010490/AKT/2013; Ivena Tiono (32409027)",
  "subjects": "AUDITING; STOCK EXCHANGE-INDONESIA; FINANCIAL STATEMeNTS"
}