{
  "id": "3003",
  "title": "Analisa kemampuan co-branding Ades dengan Coca-Cola dalam meningkatkan citra produk AMDK-nya ditinjau dari atribut-atribut produk: studi eksperimen mahasiswa jurusan manajemen",
  "abstract": "Co-branding adalah fenomena baru dalam dunia pemasaran, dimana dua perusahaan atau lebih bergabung dan melakukan segala macam aktivitas untuk memberikan nilai tambah atas produk hasil co-brandmg tersebut. Meningkatnya citra produk dalam persepsi konsumen adalah salah satu efek dari co-brandmg. Citra produk hasil co-branding dapat diukur melalui penilaian sikap konsumen terhadap kinerja dari atribut-atribut produk tersebut. Apabila kinerja atribut-atribut produk tersebut sesuai atau bahkan melebihi harapan konsumen, maka sikap konsumen positif yang berarti co-branding tersebut mampu meningkatkan citra produk. Sebaliknya apabila kinerja atribut-atribut produk tersebut tidak sesuai atau jauh di bawah harapan konsumen, maka sikap konsumen negatif yang berarti co-brandmg tersebut tidak mampu meningkatkan citra produk.",
  "creators": "MICHAEL ADIWIJAYA",
  "contributors": "Peter Remy Yosy Pasla (Advisor 1); Drs. Sugiono Sugiharto, M.M., Ph.D. (Examination Committee 1)",
  "publisher": "Universitas Kristen Petra",
  "language": "Indonesian",
  "theme": "Digital Theses",
  "category": "Undergraduate Thesis",
  "sub_category": "Skripsi/Undergraduate Thesis",
  "source": "Skripsi No.02011646/MAN/2003; Michael Adiwijaya (31499314)",
  "subjects": "CONSUMERS-RESEARCH; CONSUMER BEHAVIOR; CONSUMERS-PREFERENCES"
}