{
  "id": "34237",
  "title": "Proses komunikasi interpersonal anak yang hidup terpisah dari orangtuanya",
  "abstract": "Komunikasi dalam anggota keluarga yang terdapat ayah, ibu dan anak sering sekali harus menghadapi masalah-masalah. Apalagi bagi keluarga yang anggota keluarganya tidak lengkap. Fenomena anak yang terpisah dengan orangtuanya selama bertahun-tahun, menjadi menarik untuk dikaji dari aspek-aspek komunikasi interpersonalnya. Penelitian ini bertujuan untuk melihat pemaknaan komunikasi interpersonal anak yang hidup terpisah dari orangtuanya. Metode yang digunakan adalah metode studi kasus. Hasil temuan peneliti adalah anak perempuan yang terpisah dengan ayahnya tidak merasa butuh berkomunikasi dengan orangtuanya. Sedangkan anak yang terpisah dengan ibunya memaknai komunikasi dengan orangtua merupakan sesuatu yang penting. Beberapa faktor yang ditemukan dalam mempengaruhi proses komunikasi adalah lamanya terpisah dan umur anak saat berpisah dengan orang tua. Di sisi lain intensitas berkomunikasi dan tanggung jawab orang tua merupakan hal yang penting.",
  "creators": "SINTA PUSPITA",
  "contributors": "Ido Prijana Hadi (Advisor 1); Kartika Bayu Primasanti (Advisor 2); Jandy Edipson Luik (Examination Committee 1)",
  "publisher": "Universitas Kristen Petra",
  "language": "Indonesian",
  "theme": "Digital Theses",
  "category": "Undergraduate Thesis",
  "sub_category": "Skripsi/Undergraduate Thesis",
  "source": "Skripsi No. 20011120/KOM/2015; Sinta Puspita (51411051)",
  "subjects": "INTERPERSONAL COMMUNICATION; COMMUNICATION"
}