{
  "id": "34866",
  "title": "Perancangan sistem PPIC di PT Mustikarama Citraperdana",
  "abstract": "PT Mustikarama Citraperdana adalah perusahaan yang bergerak di bidang pembuatan lemari besi. Perusahaan ini semakin berkembang ditandai dengan semakin meningkatnya jumlah pesanan, volume produksi, dan jumlah jenis produk. Masalah yang dihadapi oleh PT Mustikarama Citraperdana adalah pengiriman pesanan pelanggan yang tidak sesuai dengan jadwal yang ditentukan dengan prosentase sebesar 52,44%. Pengamatan awal, ketidaktepatan waktu dalam pengiriman pesanan disebabkan oleh masalah perencanaan produksi yang tidak tepat. Tugas Akhir ini akan memberikan rancangan perbaikan untuk mengatasi masalah perencanaan produksi yang menyebabkan perusahaan mengalami kendala dalam pemenuhan waktu pemesanan. Rancangan perbaikan yang diberikan dalam bentuk langkah-langkah perencanaan produksi dan pengendalian persediaan bahan baku.",
  "creators": "NOVIA VERONIKA YULIANI",
  "contributors": "Herri Christian Palit (Advisor 1); Jani Rahardjo (Examination Committee 1)",
  "publisher": "Universitas Kristen Petra",
  "language": "Indonesian",
  "theme": "Digital Theses",
  "category": "Undergraduate Thesis",
  "sub_category": "Skripsi/Undergraduate Thesis",
  "source": "Skripsi No. 01021791/IND/2015; Novia Veronika (25411049)",
  "subjects": "PRODUCTION MANAGEMENT; MANUFACTURING PLANNING; MANUFACTURING INDUSTRIES"
}