{
  "id": "38213",
  "title": "Analisa pengaruh kepuasan konsumen atas experiential marketing terhadap loyalitas konsumen di Zoom Hotel Surabaya",
  "abstract": "Kepuasan konsumen adalah tingkat perasaan konsumen setelah membandingkan antara kinerja atau hasil yang dirasakan dengan harapannya. Experiential Marketing adalah konsep pemasaran yang memberikan pengalaman unik dan tak terlupakan kepada konsumen dengan melibatkan emosi konsumen. Kepuasan konsumen atas experiential marketing terdiri dari kepuasan sense, feel, think and relate. Penelitian ini bertujuan mengetahui pengaruh kepuasan konsumen atas experiential marketing terhadap loyalitas konsumen di Zoom Hotel Surabaya. Penelitian ini melibatkan 100 konsumen di Zoom Hotel Surabaya. Hasil penelitian menunjukkan bahwa kepuasan sense memiliki pengaruh positif, signifikan dan paling dominan terhadap loyalitas konsumen. Sedangkan kepuasan feel and think memiliki pengaruh positif namun tidak berpengaruh secara signifikan. Kepuasan relate berpengaruh negatif dan tidak berpengaruh secara signifikan.",
  "creators": "FANNY HALIM; KARINA",
  "contributors": "Fransisca Andreani (Advisor and Examination Committee)",
  "publisher": "Universitas Kristen Petra",
  "language": "Indonesian",
  "theme": "Digital Theses",
  "category": "Undergraduate Thesis",
  "sub_category": "Skripsi/Undergraduate Thesis",
  "source": "Skripsi No. 33010600/MAN/2016; Fanny Halim (33412070), Karina (33412133)",
  "subjects": "HOTELS-MARKETING-CONSUMERS-RESEARCH; HOTELS-MARKETING MANAGEMENT; HOTELS-MANAGEMENT; CONSUMER SATISFACTION."
}