{
  "id": "39300",
  "title": "Pengaruh motivasi kerja dan kepuasan kerja terhadap kinerja karyawan PT Cocacola Amatil Indonesia Surabaya",
  "abstract": "Penelitian ini bertujuan untuk mengetahui pengaruh motivasi kerja dan kepuasan kerja terhadap kinerja karyawan PT Cocacola Amatil Indonesia Surabaya. Jumlah sampel yang digunakan dalam penelitian ini sebanyak 110 responden dengan metode pengumpulan data yaitu menggunakan kuesioner. Analisis yang digunakan dalam penelitian ini adalah uji regresi linier berganda. Hasil penelitian ini menunjukkan bahwa motivasi kerja tidak berpengaruh signifikan terhadap kinerja karyawan, kepuasan kerja berpengaruh signifikan terhadap kinerja karyawan dan kepuasan kerja memberi pengaruh lebih dominan terhadap kinerja karyawan daripada motivasi kerja.",
  "creators": "IVAN TIMOTHY",
  "contributors": "Thomas Santoso (Advisor and Examination Committee)",
  "publisher": "Universitas Kristen Petra",
  "language": "Indonesian",
  "theme": "Digital Theses",
  "category": "Undergraduate Thesis",
  "sub_category": "Skripsi/Undergraduate Thesis",
  "source": "Skripsi No. 31011261/ MAN/2017; Ivan Timothy (31413028)",
  "subjects": "WORK MOTIVATION; PERSONNEL MANAGEMENT; JOB SATISFACTION"
}