{
  "id": "43351",
  "title": "Pengaruh design and use of management control system terhadap firm performance dengan organizational learning sebagai variabel mediasi di Indonesia",
  "abstract": "Penelitian ini bertujuan untuk mengetahui pengaruh dari design dan use of management control system terhadap firm performance melalui organizational learning sebagai variabel mediasi di Indonesia. Management control system diukur dengan menggunakan komponen design dan use of MCS, organizational learning diukur dengan menggunakan komponen akuisisi pengetahuan, distribusi informasi, interpretasi informasi, dan memori organisasi. Sementara firm performance diukur dengan menggunakan komponen kinerja keuangan dan kinerja operasional. Penelitian ini dilakukan dengan membagi kuesioner ke berbagai perusahaan di Indonesia dengan hasil akhir sampel sebanyak 35 perusahaan. Hasil penelitian menunjukkan adanya pengaruh yang signifikan dari management control system terhadap organizational learning dan dari organizational learning terhadap firm performance. Sementara pengaruh dari management control system terhadap firm performance adalah tidak signifikan secara langsung. Hasil penelitian menunjukkan bahwa organizational learning diperlukan untuk menjembatani hubungan antara management control system dan firm performance. Hasil ini sesuai dengan teori Resource Based View.",
  "creators": "VANNY LISAYANI WIJAYA",
  "contributors": "Saarce Elsye Hatane (Advisor 1); Devie (Examination Committee 1); Priskila (Examination Committee 2)",
  "publisher": "Universitas Kristen Petra",
  "language": "Indonesian",
  "theme": "Digital Theses",
  "category": "Undergraduate Thesis",
  "sub_category": "Skripsi/Undergraduate Thesis",
  "source": "Skripsi No. 32011272/AKT/2019; Vanny Lisayani Wijaya (32415071)",
  "subjects": "ORGANIZATIONAL LEARNING"
}