{
  "id": "4409",
  "title": "Graha seni lukis kontemporer di Surabaya",
  "abstract": "Graha Seni Lukis Kontemporer di Surabaya ini merupakan proyek milik swasta yang bergerak di bidang jasa pariwisata dan pendidikan. Obyek koleksi berupa karya ? karya seni Lukis Kontemporer baik dari dalam maupun luar negeri. Fasilitas yang direncanakan meliputi ruang pamer tetap, ruang pamer temporer, gedung serba guna, perpustakaan, toko souvenir, restoran, cafetaria, lobby, mess seniman ruang kantor, ruang rapat, ruang kurator, ruang penerimaan/pengiriman, ruang penyimpanan sementara, ruang reproduksi, ruang konservasi dan restorasi, gudang koleksi, ruang preparasi, ruang komputer, dan gudang bahan/alat. Sesuai dengan obyek koleksinya konsep yang diusung adalah kesan kontemporer dengan interpretasi kebebasan berekspresi pada bangunan. Dalam perancangan menggunakan bentuk geometri seperti kotak dipadukan dengan bentukan yang ledih dinamis..",
  "creators": "ZANDY ISADA",
  "contributors": "Frans Soehartono (Advisor 1); Rony Gunawan (Examination Committee 1)",
  "publisher": "Universitas Kristen Petra",
  "language": "Indonesian",
  "theme": "Digital Theses",
  "category": "Undergraduate Thesis",
  "sub_category": "Laporan Perancangan Arsitektur",
  "source": "Laporan Perancangan Arsitektur No. 02132391/ARS/2006; Zandy Isada (22402077)",
  "subjects": "ART MUSEUMS; ART FACILITIES"
}