{
  "id": "46789",
  "title": "Studi tentang teknik penyajian audio visual program acara pada stasiun Malang TV",
  "abstract": "Studi Tentang Teknik Penyajian ini bertujuan untuk menghadirkan suatu program acara yang disampaikan sebagai informasi, khususnya untuk para mahasiswa ataupun untuk masyarakat umum yang ingin mengetahui lebih dalam lagi tentang penyajian program acara yang disajikan melalui teknik penyajian audio visual lewat stasiun Malang TV. Penelitian ini melihat dan mengetahui tentang kualitas teknik penyajian audio visual, proses pembuatan acara sampai dengan penayangannya di layar kaca atau televisi. Skripsi ini dibuat dan diteliti berdasarkan data hasil riset lapangan maupun literatur sehingga diharapkan dapat menjawab tujuan yang telah dipaparkan.",
  "creators": "SUMULYAWATI",
  "contributors": "Bedjo Riyanto (Advisor 1); Ani Wijayanti Suhartono (Advisor 2); Listia (Examination Committee 1)",
  "publisher": "Universitas Kristen Petra",
  "language": "Indonesian",
  "theme": "Digital Theses",
  "category": "Undergraduate Thesis",
  "sub_category": "Skripsi/Undergraduate Thesis",
  "source": "Skripsi No. 00010864/DKV/2006; Sumulyawati (42402227)",
  "subjects": "COMMERCIAL ART; TELEVISION BROADCASTING; VISUAL COMMUNICATION; AUDIO-VISUAL EDUCATION"
}