{
  "id": "46955",
  "title": "Football swalayan",
  "abstract": "",
  "creators": "WELY; ANGELINE RIVANDIE",
  "contributors": "Sundring Pantja Djati (Advisor 1); Hatane Semuel (Examination Committee 1)",
  "publisher": "Universitas Kristen Petra",
  "language": "Indonesian",
  "theme": "Digital Theses",
  "category": "Undergraduate Thesis",
  "sub_category": "Rancangan Usaha",
  "source": "Rancangan Usaha No. 72/EM/2001; Wely (31496038), Angeline Rivandie (31496239)",
  "subjects": "SPORTS EQUIPMENT; FOOTBALL--EQUIPMENT AND SUPPLIES"
}