{
  "id": "47524",
  "title": "Perancangan desain kemasan produk Toko Kue Kering “Dewi” Semarang",
  "abstract": "Toko Kue Kering Dewi merupakan bisnis turun temurun keluarga yang menjual berbagai macam kue kering dan sus kering dengan berbagai macam varian rasa yang jarang ditemui. Sampai saat ini kemasan Kue Kering Dewi belum menunjukkan logo yang konsisten, belum adanya informasi pada kemasan, dan kemasan belum melindungi isi produk dengan baik. Oleh karena itu, dalam perancangan ini akan dibuat kemasan yang dapat melindungi isi produk di dalamnya serta dapat menggambarkan citra merek Toko Kue Kering Dewi dan terdapat informasi yang lengkap. Perancangan ini menggunakan metode analisis yaitu VIEW dan SWOT. Pada akhirnya Toko Kue Kering Dewi dapat bersaing dengan kompetitor yang ada serta terciptanya kepercanyaan masyarakat.",
  "creators": "DEVINA FLORENCIA BUDIMAN",
  "contributors": "Elisabeth Christine Yuwono (Advisor 1); Vanessa Yusuf (Advisor 2); Deddi Duto Hartanto (Examination Committee 1); Rebecca Milka Natalia Basuki (Examination Committee 2)",
  "publisher": "Universitas Kristen Petra",
  "language": "Indonesian",
  "theme": "Digital Theses",
  "category": "Undergraduate Thesis",
  "sub_category": "Desain Kemasan",
  "source": "Desain Kemasan No. 00023526/DKV/2020; Devina Florencia Budiman (42416123)",
  "subjects": "COMMERCIAL ART; GRAPHIC ARTS; LOGOS (SYMBOLS); PACKAGING--DESIGN; VISUAL COMMUNICATION"
}