{
  "id": "47758",
  "title": "Fasilitas pelatihan seni videografi di Surabaya",
  "abstract": "Video merupakan salah satu karya sebuah seni. Video sendiri dapat memberikan dampak yang cukup signifikan bagi perkembangan pola pikir masyarakat sekitarnya. Peminat seni videografi juga cukup relatif banyak pada zaman ini. Mulai anak-anak remaja hingga para pemuda-pemudi. Dikarenakan banyak peminat seni videografi, mereka jarang menemukan tempat yang tepat untuk mereka belajar, mengembangkan kemampuan mereka, serta mencari komunitas yang juga bergerak dibidang videografi dan pada akhirnya berujung di café-café yang kurang nyaman bagi mereka untuk belajar. Oleh karena itu, diusulkan perancangan arsitektur Fasilitas Pelatihan Seni Videografi di Surabaya, sebagai sebuah desain baru, yang mewadahi kebutuhan, membentuk sebuah komunitas, dan sarana bagi masyrakat yang ingin belajar. Hal ini dilakukan dengan menerapkan konsep desain yang memperkenalkan proses pembuatan sebuah video.",
  "creators": "PRIANTO WELLY HO",
  "contributors": "Andhi Wijaya (Advisor 1); Christine Wonoseputro (Advisor 2); Anik Juniwati (Advisor 3); Ir. Bisatya Widadya Maer, M.T. (Examination Committee 1); Riduan Sukardi (Examination Committee 2); Aris Budhiyanto, S.T., M.Sc., Ph.D. (Examination Committee 3)",
  "publisher": "Universitas Kristen Petra",
  "language": "Indonesian",
  "theme": "Digital Theses",
  "category": "Undergraduate Thesis",
  "sub_category": "Laporan Perancangan Arsitektur",
  "source": "Skripsi No. 01024134/ARS/2020; Prianto Welly Ho (22416152)",
  "subjects": "ART FACILITIES"
}