{
  "id": "51879",
  "title": "Analisa pressure loss pada sistem perpipaan pada forging plant di PT Komatsu undercarriage Indonesia",
  "abstract": "Saat ini forging plant di PT Komatsu Undercarriage Indonesia (KUI) memiliki 4 ruang kompresor dengan total kompresor sebanyak 26 unit. PT. KUI menggunakan kompresor bertipe screw dalam proses produksinya. Penggunaan energi listrik terbesar diberikan oleh factory 4 yaitu pada bagian forging plant yang memiliki 5 mesin hammer dengan kapasitas 3, 6 dan 6.8 ton. Sehingga, jalur perpipaan udara bertekanan yang ada perlu dilakukan pengecekan apakah jalur perpipaan sudah baik, yang dilihat dari penurunan tekanan menuju titik yang telah ditentukan. Dari hasil-hasil analisa yang telah dilakukan, didapati bahwa penurunan tekanan yang terjadi pada titik yang telah ditentukan tidak melebihi 10% dari tekanan maksimal yang diberikan oleh kompresor, yakni 6.2 Bar. Penurunan tekanan tertinggi hanya sebesar 7.93%, sehingga dapat disimpulkan bahwa jalur perpipaan yang digunakan sudah baik. Berdasarkan analisa, diberikan beberapa rekomendasi di antaranya: pemasangan flow transmitter pada pipa aliran udara bertekanan yang disuplai ke mesin yang digunakan, pemasangan air dryer, memindahkan kompresor baru dari compressor room 1 ke compressor room 2 agar kelebihan suplai pada mesin hammer berkapasitas 3 ton tidak terjadi dan menerapkan analisa yang dilakukan ke seluruh wilayah factory.",
  "creators": "BRITDEY BANNE TANDIRERUNG",
  "contributors": "Hariyo Priambudi Setyo Pratomo, S.T., M.Phil. (Advisor 1); Ekadewi Anggraini Handoyo (Examination Committee 1); Fandi Dwiputra Suprianto, S.T., M.Sc. (Examination Committee 2)",
  "publisher": "Universitas Kristen Petra",
  "language": "Indonesian",
  "theme": "Digital Theses",
  "category": "Undergraduate Thesis",
  "sub_category": "Skripsi/Undergraduate Thesis",
  "source": "Skripsi No. 02011442/MES/2021; Britdey Banne Tandirerung (C12170082)",
  "subjects": "AIRPLANES--AIR DUCTS"
}