{
  "id": "52180",
  "title": "Studi banding pengecoran sentrifugal vertikal dengan gravitasi ditinjau dari sifat kekerasan dan struktur mikro",
  "abstract": "Sifat mekanis benda hasil pengecoran tergantung pada bentuk dan ukuran butir serta tingkat porositas. Pengecoran sentrifugal memiliki kemampuan untuk meningkatkan sifat mekanis produk pengecoran gravitasi dengan memperkecil ukuran butir dan mengurangi porositas. Tujuan penelitian ini adalah mengetahui seberapa besar perbedaan antara hasil pengecoran sentrifiigal dengan pengecoran gravitasi. Penelitian dilakukan dengan membandingkan hasil pengecoran sentrifugal vertikal dan gravitasi. Kedua metode pengecoran dilakukan dengan menggunakan cetakan green sand yang sama. Kecepatan optimal untuk pengecoran sentrifugal vertikal dengan menggimakan cetakan green sand adalah 298 rpm. Analisa terhadap kedua metode ditinjau dari sifat kekerasan dan struktur mikro. Logam penelitian adalah paduan aluminium 512.0 (LM23P). Hasil penelitian menunjukkan bahwa pengecoran sentrifugal menghasilkan struktur dengan dendrit yang lebih kecil daripada pengecoran gravitasi. Pengecoran sentrifiigal juga mampu mengurangi porositas penyusutan pada daerah sumbu putar. Peningkatan kekerasan oleh pengecoran sentrifugal hanya teqadi akibat pengurangan porositas dan tidak ada perbaikan akibat perbedaan ukuran dendrit.",
  "creators": "AYUSTAPRANA ARIEF",
  "contributors": "Soejono Tjitro (Advisor 1); Prof. Dr. Juliana Anggono, S.T., M.Sc. (Examination Committee 1)",
  "publisher": "Universitas Kristen Petra",
  "language": "Indonesian",
  "theme": "Digital Theses",
  "category": "Undergraduate Thesis",
  "sub_category": "Skripsi/Undergraduate Thesis",
  "source": "Skripsi No. 01/0692/MES/2005; Ayustapr^na Arief (24499003)",
  "subjects": "CENTRIFUGAL CASTING"
}