{
  "id": "54012",
  "title": "Perancangan manual SMK3 berdasarkan ISO 45001 tahun 2018 klausul 8 dan 9 di Universitas Kristen Petra",
  "abstract": "Keselamatan dan Kesehatan Kerja (K3) merupakan faktor yang penting untuk diterapkan dan dilakukan dalam suatu perusahaaan. Universitas Kristen Petra ingin memberikan rasa aman, nyaman, dan sehat kepada seluruh sivitasnya, dengan dirancangkan manual SMK3 berdasarkan ISO 45001 tahun 2018. Sebelum K3 diterapkan, perlu adanya perancangan terlebih dahulu. Terdapat organisasi internasional yang membahas tentang standarisasi yang berkaitan dengan keselamatan dan kesehatan kerja yaitu ISO 45001 tahun 2018. Perancangan dilakukan dengan mengamati lingkungan Universitas Kristen Petra, pengumpulan data, penentuan persyaratan ISO 45001:2018 klausul 8 dan 9, audit data dengan membandingkan kondisi universitas dengan standar ISO 45001:2018 klausul 8 dan 9, merencang manual sistem manajemen SMK3 dengan persyaratan ISO 45001:2018 klausul 8 dan 9, dan melakukan validasi. Setelah dilakukan perancangan, prosedur yang telah dibuat pada klausul 8 adalah sebanyak 18 prosedur dan untuk prosedur yang telah dibuat pada klausul 9 adalah sebanyak 5 prosedur.",
  "creators": "YOSHUA LIMANTO",
  "contributors": "Jani Rahardjo (Advisor 1); Kriswanto Widiawan (Examination Committee 1)",
  "publisher": "Universitas Kristen Petra",
  "language": "Indonesian",
  "theme": "Digital Theses",
  "category": "Undergraduate Thesis",
  "sub_category": "Skripsi/Undergraduate Thesis",
  "source": "Skripsi No. 03022554/IND/2022; Yoshua Limanto (C13180086)",
  "subjects": "STANDARD OPERATING PROCEDURE; UNIVERSITIES AND COLLEGES--SAFETY MEASURES"
}