{
  "id": "6253",
  "title": "Representasi disfungsi keluarga dalam film \"Virgin\"",
  "abstract": "Film Virgin adalah sebuah film yang mengangkat tema persahabatan di era globalisasi yang sarat dengan pengaruh budaya asing. Disfungsi keluarga menjadi salah satu penyebab gaya hidup negatif remaja. Menggunakan metode semiotika televisi John Fiske dengan unit analisis paradigma dan sintagma level realitas, level representasi, dan level ideologi, peneliti ingin mengetahui bagaimana representasi disfungsi keluarga dalam film Virgin. Hasil penelitian ini menunjukkan bahwa representasi disfungsi keluarga dapat dirujuk dari karakter dan gaya hidup remaja. Disfungsi keluarga yang terjadi dalam hal yang berbeda-beda pada setiap latar keluarga remaja yang berbeda-beda pula. Pada akhirnya, penelitian ini dapat memberikan wacana tersendiri bagi keluarga Indonesia mengenai pentingnya keberfungsian sebuah keluarga.",
  "creators": "RUTH PRISCILLA HUTUBESSY",
  "contributors": "SRI MOERDIJATI (Advisor 1); Yola Damayanti Gani (Advisor 2); YULI NUGRAHENI (Examination Committee 1)",
  "publisher": "Universitas Kristen Petra",
  "language": "Indonesian",
  "theme": "Digital Theses",
  "category": "Undergraduate Thesis",
  "sub_category": "Skripsi/Undergraduate Thesis",
  "source": "Skripsi No. 20010218/KOM/2007; Ruth Priscilla Hutubessy (51402060)",
  "subjects": "FAMILY; COMMUNICATION; MOTION PICTURES"
}